{"tipoJogo":"MEGA_SENA","numero":1035,"nomeMunicipioUFSorteio":"SÃO PAULO, SP","dataApuracao":"31/12/2008","valorArrecadado":0,"valorEstimadoProximoConcurso":45000000,"valorAcumuladoProximoConcurso":37025110.94,"valorAcumuladoConcursoEspecial":1066869.15,"valorAcumuladoConcurso_0_5":4694224.16,"acumulado":true,"indicadorConcursoEspecial":1,"dezenasSorteadasOrdemSorteio":["051","060","001","011","059","026"],"listaResultadoEquipeEsportiva":null,"numeroJogo":2,"nomeTimeCoracaoMesSorte":"","tipoPublicacao":3,"observacao":"","localSorteio":"Caminhão da Sorte","dataProximoConcurso":"03/01/2009","numeroConcursoAnterior":1034,"numeroConcursoProximo":1036,"valorTotalPremioFaixaUm":0,"numeroConcursoFinal_0_5":1040,"listaDezenas":["001","011","026","051","059","060"],"listaDezenasSegundoSorteio":null,"listaMunicipioUFGanhadores":[],"listaRateioPremio":[{"faixa":1,"numeroDeGanhadores":0,"valorPremio":0,"descricaoFaixa":"6 acertos"},{"faixa":2,"numeroDeGanhadores":289,"valorPremio":14028.04,"descricaoFaixa":"5 acertos"},{"faixa":3,"numeroDeGanhadores":19044,"valorPremio":212.88,"descricaoFaixa":"4 acertos"}],"id":null,"ultimoConcurso":true,"exibirDetalhamentoPorCidade":true,"premiacaoContingencia":null}