{"tipoJogo":"MEGA_SENA","numero":2072,"nomeMunicipioUFSorteio":"ITABELA, BA","dataApuracao":"25/08/2018","valorArrecadado":49882350,"valorEstimadoProximoConcurso":40000000,"valorAcumuladoProximoConcurso":33066374.91,"valorAcumuladoConcursoEspecial":46376847.88,"valorAcumuladoConcurso_0_5":8699929.77,"acumulado":true,"indicadorConcursoEspecial":1,"dezenasSorteadasOrdemSorteio":["022","013","010","020","012","054"],"listaResultadoEquipeEsportiva":null,"numeroJogo":2,"nomeTimeCoracaoMesSorte":"","tipoPublicacao":3,"observacao":"","localSorteio":"Caminhão da Sorte","dataProximoConcurso":"29/08/2018","numeroConcursoAnterior":2071,"numeroConcursoProximo":2073,"valorTotalPremioFaixaUm":0,"numeroConcursoFinal_0_5":2075,"listaDezenas":["010","012","013","020","022","054"],"listaDezenasSegundoSorteio":null,"listaMunicipioUFGanhadores":[],"listaRateioPremio":[{"faixa":1,"numeroDeGanhadores":0,"valorPremio":0,"descricaoFaixa":"6 acertos"},{"faixa":2,"numeroDeGanhadores":135,"valorPremio":21303.29,"descricaoFaixa":"5 acertos"},{"faixa":3,"numeroDeGanhadores":8860,"valorPremio":463.71,"descricaoFaixa":"4 acertos"}],"id":null,"ultimoConcurso":true,"exibirDetalhamentoPorCidade":true,"premiacaoContingencia":null}