{"tipoJogo":"MEGA_SENA","numero":2106,"nomeMunicipioUFSorteio":"CRICIÚMA, SC","dataApuracao":"12/12/2018","valorArrecadado":50688848,"valorEstimadoProximoConcurso":42000000,"valorAcumuladoProximoConcurso":35176471.32,"valorAcumuladoConcursoEspecial":65263127.68,"valorAcumuladoConcurso_0_5":6192404.78,"acumulado":true,"indicadorConcursoEspecial":1,"dezenasSorteadasOrdemSorteio":["027","003","039","040","036","043"],"listaResultadoEquipeEsportiva":null,"numeroJogo":2,"nomeTimeCoracaoMesSorte":"","tipoPublicacao":3,"observacao":"","localSorteio":"CAMINHÃO DA SORTE","dataProximoConcurso":"15/12/2018","numeroConcursoAnterior":2105,"numeroConcursoProximo":2107,"valorTotalPremioFaixaUm":0,"numeroConcursoFinal_0_5":2110,"listaDezenas":["003","027","036","039","040","043"],"listaDezenasSegundoSorteio":null,"listaMunicipioUFGanhadores":[],"listaRateioPremio":[{"faixa":1,"numeroDeGanhadores":0,"valorPremio":0,"descricaoFaixa":"6 acertos"},{"faixa":2,"numeroDeGanhadores":82,"valorPremio":35639.55,"descricaoFaixa":"5 acertos"},{"faixa":3,"numeroDeGanhadores":5610,"valorPremio":744.19,"descricaoFaixa":"4 acertos"}],"id":null,"ultimoConcurso":true,"exibirDetalhamentoPorCidade":true,"premiacaoContingencia":null}