{"tipoJogo":"MEGA_SENA","numero":298,"nomeMunicipioUFSorteio":"Porto Alegre, RS","dataApuracao":"22/09/2001","valorArrecadado":0,"valorEstimadoProximoConcurso":0,"valorAcumuladoProximoConcurso":0,"valorAcumuladoConcursoEspecial":0,"valorAcumuladoConcurso_0_5":6411163.97,"acumulado":false,"indicadorConcursoEspecial":1,"dezenasSorteadasOrdemSorteio":["022","034","024","023","005","060"],"listaResultadoEquipeEsportiva":null,"numeroJogo":2,"nomeTimeCoracaoMesSorte":"","tipoPublicacao":3,"observacao":"Estimativa de prêmio (sena) próximo concurso: R$500.000,00.","localSorteio":"Caminhão da Sorte","dataProximoConcurso":"26/09/2001","numeroConcursoAnterior":297,"numeroConcursoProximo":299,"valorTotalPremioFaixaUm":0,"numeroConcursoFinal_0_5":300,"listaDezenas":["005","022","023","024","034","060"],"listaDezenasSegundoSorteio":null,"listaMunicipioUFGanhadores":[{"posicao":1,"ganhadores":1,"municipio":"","uf":"PR","nomeFatansiaUL":"","serie":""}],"listaRateioPremio":[{"faixa":1,"numeroDeGanhadores":1,"valorPremio":2994572.21,"descricaoFaixa":"6 acertos"},{"faixa":2,"numeroDeGanhadores":50,"valorPremio":17440.22,"descricaoFaixa":"5 acertos"},{"faixa":3,"numeroDeGanhadores":4372,"valorPremio":198.71,"descricaoFaixa":"4 acertos"}],"id":null,"ultimoConcurso":true,"exibirDetalhamentoPorCidade":true,"premiacaoContingencia":null}