{"tipoJogo":"MEGA_SENA","numero":579,"nomeMunicipioUFSorteio":"BRASÍLIA, DF","dataApuracao":"10/07/2004","valorArrecadado":0,"valorEstimadoProximoConcurso":0,"valorAcumuladoProximoConcurso":0,"valorAcumuladoConcursoEspecial":0,"valorAcumuladoConcurso_0_5":8008407.15,"acumulado":false,"indicadorConcursoEspecial":1,"dezenasSorteadasOrdemSorteio":["015","034","039","017","004","009"],"listaResultadoEquipeEsportiva":null,"numeroJogo":2,"nomeTimeCoracaoMesSorte":"","tipoPublicacao":3,"observacao":"Estimativa de prêmio (SENA) próximo concurso: R$10.000.000,00 (DEZ MILHÕES DE REAIS).","localSorteio":"Caminhão da Sorte","dataProximoConcurso":"14/07/2004","numeroConcursoAnterior":578,"numeroConcursoProximo":580,"valorTotalPremioFaixaUm":0,"numeroConcursoFinal_0_5":580,"listaDezenas":["004","009","015","017","034","039"],"listaDezenasSegundoSorteio":null,"listaMunicipioUFGanhadores":[{"posicao":1,"ganhadores":1,"municipio":"","uf":"PB","nomeFatansiaUL":"","serie":""}],"listaRateioPremio":[{"faixa":1,"numeroDeGanhadores":1,"valorPremio":1175432.13,"descricaoFaixa":"6 acertos"},{"faixa":2,"numeroDeGanhadores":90,"valorPremio":7463.06,"descricaoFaixa":"5 acertos"},{"faixa":3,"numeroDeGanhadores":5172,"valorPremio":129.38,"descricaoFaixa":"4 acertos"}],"id":null,"ultimoConcurso":true,"exibirDetalhamentoPorCidade":true,"premiacaoContingencia":null}