{"tipoJogo":"MEGA_SENA","numero":1241,"nomeMunicipioUFSorteio":"COLÍDER, MT","dataApuracao":"18/12/2010","valorArrecadado":38582506,"valorEstimadoProximoConcurso":26000000,"valorAcumuladoProximoConcurso":24042571.82,"valorAcumuladoConcursoEspecial":58684766.59,"valorAcumuladoConcurso_0_5":4871536.89,"acumulado":true,"indicadorConcursoEspecial":1,"dezenasSorteadasOrdemSorteio":["013","026","025","010","028","045"],"listaResultadoEquipeEsportiva":null,"numeroJogo":2,"nomeTimeCoracaoMesSorte":"","tipoPublicacao":3,"observacao":"","localSorteio":"Caminhão da Sorte","dataProximoConcurso":"20/12/2010","numeroConcursoAnterior":1240,"numeroConcursoProximo":1242,"valorTotalPremioFaixaUm":0,"numeroConcursoFinal_0_5":1245,"listaDezenas":["010","013","025","026","028","045"],"listaDezenasSegundoSorteio":null,"listaMunicipioUFGanhadores":[],"listaRateioPremio":[{"faixa":1,"numeroDeGanhadores":0,"valorPremio":0,"descricaoFaixa":"6 acertos"},{"faixa":2,"numeroDeGanhadores":181,"valorPremio":12479.72,"descricaoFaixa":"5 acertos"},{"faixa":3,"numeroDeGanhadores":12556,"valorPremio":257,"descricaoFaixa":"4 acertos"}],"id":null,"ultimoConcurso":true,"exibirDetalhamentoPorCidade":true,"premiacaoContingencia":null}