{"tipoJogo":"MEGA_SENA","numero":1686,"nomeMunicipioUFSorteio":"ROSEIRA, SP","dataApuracao":"14/03/2015","valorArrecadado":59111810,"valorEstimadoProximoConcurso":3000000,"valorAcumuladoProximoConcurso":0,"valorAcumuladoConcursoEspecial":12500397,"valorAcumuladoConcurso_0_5":7353210.44,"acumulado":false,"indicadorConcursoEspecial":1,"dezenasSorteadasOrdemSorteio":["044","037","009","055","014","046"],"listaResultadoEquipeEsportiva":null,"numeroJogo":2,"nomeTimeCoracaoMesSorte":"","tipoPublicacao":3,"observacao":"","localSorteio":"Caminhão da Sorte","dataProximoConcurso":"18/03/2015","numeroConcursoAnterior":1685,"numeroConcursoProximo":1687,"valorTotalPremioFaixaUm":0,"numeroConcursoFinal_0_5":1690,"listaDezenas":["009","014","037","044","046","055"],"listaDezenasSegundoSorteio":null,"listaMunicipioUFGanhadores":[{"posicao":1,"ganhadores":1,"municipio":"SANTA TERESA","uf":"ES","nomeFatansiaUL":"","serie":""},{"posicao":1,"ganhadores":1,"municipio":"IBIUNA","uf":"SP","nomeFatansiaUL":"","serie":""},{"posicao":1,"ganhadores":1,"municipio":"SERTÃOZINHO","uf":"SP","nomeFatansiaUL":"","serie":""}],"listaRateioPremio":[{"faixa":1,"numeroDeGanhadores":3,"valorPremio":8927028.65,"descricaoFaixa":"6 acertos"},{"faixa":2,"numeroDeGanhadores":117,"valorPremio":29578.87,"descricaoFaixa":"5 acertos"},{"faixa":3,"numeroDeGanhadores":8999,"valorPremio":549.38,"descricaoFaixa":"4 acertos"}],"id":null,"ultimoConcurso":true,"exibirDetalhamentoPorCidade":true,"premiacaoContingencia":null}