{"tipoJogo":"MEGA_SENA","numero":2365,"nomeMunicipioUFSorteio":"SÃO PAULO, SP","dataApuracao":"24/04/2021","valorArrecadado":41637028.5,"valorEstimadoProximoConcurso":28000000,"valorAcumuladoProximoConcurso":22515609.47,"valorAcumuladoConcursoEspecial":21840149.09,"valorAcumuladoConcurso_0_5":2779646.38,"acumulado":true,"indicadorConcursoEspecial":1,"dezenasSorteadasOrdemSorteio":["044","050","017","028","037","001"],"listaResultadoEquipeEsportiva":null,"numeroJogo":2,"nomeTimeCoracaoMesSorte":"\u0000\u0000\u0000\u0000\u0000\u0000\u0000\u0000\u0000\u0000\u0000\u0000\u0000\u0000\u0000\u0000\u0000","tipoPublicacao":3,"observacao":"","localSorteio":"ESPAÇO LOTERIAS CAIXA","dataProximoConcurso":"28/04/2021","numeroConcursoAnterior":2364,"numeroConcursoProximo":2366,"valorTotalPremioFaixaUm":0,"numeroConcursoFinal_0_5":2370,"listaDezenas":["001","017","028","037","044","050"],"listaDezenasSegundoSorteio":null,"listaMunicipioUFGanhadores":[],"listaRateioPremio":[{"faixa":1,"numeroDeGanhadores":0,"valorPremio":0,"descricaoFaixa":"6 acertos"},{"faixa":2,"numeroDeGanhadores":40,"valorPremio":60015.09,"descricaoFaixa":"5 acertos"},{"faixa":3,"numeroDeGanhadores":2940,"valorPremio":1166.47,"descricaoFaixa":"4 acertos"}],"id":null,"ultimoConcurso":true,"exibirDetalhamentoPorCidade":true,"premiacaoContingencia":null}